Metadata-Version: 2.1
Name: XMIssion
Version: 0.9.5
Summary: XMIssion XMI/AWS/HET Gnome File Manager
Home-page: https://github.com/mainframed/xmission
Author: Philip Young
Author-email: mainframed767@gmail.com
License: GPLv2
Platform: UNKNOWN
Requires-Python: >=3.8
